tests/__init__.py
tests/test_backtest.py
tests/test_binance_inverse_futures.py
tests/test_broker.py
tests/test_candle_service.py
tests/test_completed_trade.py
tests/test_conflicting_orders.py
tests/test_exchange.py
tests/test_helpers.py
tests/test_import_candles.py
tests/test_indicators.py
tests/test_isolated_backtest.py
tests/test_metrics.py
tests/test_order.py
tests/test_parent_strategy.py
tests/test_position.py
tests/test_router.py
tests/test_state_candle.py
tests/test_state_exchanges.py
tests/test_state_logs.py
tests/test_state_orderbook.py
tests/test_state_orders.py
tests/test_state_ticker.py
tests/test_state_trades.py
tests/test_utils.py
tests/utils.py
tests/data/__init__.py
tests/data/test_candles_0.py
tests/data/test_candles_1.py
tests/data/test_candles_indicators.py
xdeen/__init__.py
xdeen/config.py
xdeen/helpers.py
xdeen/utils.py
xdeen/version.py
xdeen/enums/__init__.py
xdeen/exceptions/__init__.py
xdeen/exchanges/__init__.py
xdeen/exchanges/exchange.py
xdeen/exchanges/sandbox/Sandbox.py
xdeen/exchanges/sandbox/__init__.py
xdeen/factories/__init__.py
xdeen/factories/candle_factory.py
xdeen/factories/order_factory.py
xdeen/indicators/__init__.py
xdeen/indicators/acosc.py
xdeen/indicators/ad.py
xdeen/indicators/adosc.py
xdeen/indicators/adx.py
xdeen/indicators/adxr.py
xdeen/indicators/alligator.py
xdeen/indicators/alma.py
xdeen/indicators/ao.py
xdeen/indicators/apo.py
xdeen/indicators/aroon.py
xdeen/indicators/aroonosc.py
xdeen/indicators/atr.py
xdeen/indicators/avgprice.py
xdeen/indicators/bandpass.py
xdeen/indicators/beta.py
xdeen/indicators/bollinger_bands.py
xdeen/indicators/bollinger_bands_width.py
xdeen/indicators/bop.py
xdeen/indicators/cc.py
xdeen/indicators/cci.py
xdeen/indicators/cfo.py
xdeen/indicators/cg.py
xdeen/indicators/chande.py
xdeen/indicators/chop.py
xdeen/indicators/cksp.py
xdeen/indicators/cmo.py
xdeen/indicators/correl.py
xdeen/indicators/correlation_cycle.py
xdeen/indicators/cvi.py
xdeen/indicators/cwma.py
xdeen-0.0.1.dist-info/LICENSE
xdeen-0.0.1.dist-info/METADATA
xdeen-0.0.1.dist-info/WHEEL
xdeen-0.0.1.dist-info/entry_points.txt
xdeen-0.0.1.dist-info/top_level.txt
xdeen-0.0.1.dist-info/RECORD
