Metadata-Version: 2.1
Name: xdeen
Version: 0.0.1
Summary: AI trading network for cryptocurrencies
Home-page: https://xdeen.net
Author: Sherif Light
Author-email: sherif@xdeen.net
License: UNKNOWN
Project-URL: Documentation, https://docs.xdeen.net
Project-URL: Say Thanks!, https://xdeen.net/discord
Project-URL: Source, https://github.com/xdeen-ai/xdeen
Project-URL: Tracker, https://github.com/xdeen-ai/xdeen/issues
Platform: UNKNOWN
Classifier: Programming Language :: Python :: 3
Classifier: License :: OSI Approved :: MIT License
Classifier: Operating System :: OS Independent
Requires-Python: >=3.8
License-File: LICENSE
Requires-Dist: arrow (==1.2.1)
Requires-Dist: blinker (==1.4)
Requires-Dist: click (==8.0.3)
Requires-Dist: matplotlib (==3.5.1)
Requires-Dist: mplfinance (==0.12.8b6)
Requires-Dist: newtulipy (==0.4.6)
Requires-Dist: numpy (==1.22.2)
Requires-Dist: numpy-groupies (==0.9.14)
Requires-Dist: pandas (==1.4.0)
Requires-Dist: peewee (==3.14.8)
Requires-Dist: psycopg2-binary (==2.9.2)
Requires-Dist: pydash (==5.1.0)
Requires-Dist: pytest (==6.2.5)
Requires-Dist: PyWavelets (==1.2.0)
Requires-Dist: quantstats (==0.0.47)
Requires-Dist: requests (==2.26.0)
Requires-Dist: scipy (==1.8.0)
Requires-Dist: statsmodels (==0.13.2)
Requires-Dist: TA-Lib (==0.4.24)
Requires-Dist: tabulate (==0.8.9)
Requires-Dist: timeloop (==1.0.2)
Requires-Dist: websocket-client (==1.2.3)
Requires-Dist: simplejson (==3.16.0)
Requires-Dist: aioredis (==1.3.1)
Requires-Dist: redis (==4.1.4)
Requires-Dist: fastapi (==0.74.0)
Requires-Dist: uvicorn (==0.14.0)
Requires-Dist: websockets (==9.1.0)
Requires-Dist: python-dotenv (==0.19.2)
Requires-Dist: aiofiles (==0.7.0)
